verbose_chainsaw/__init__.py
verbose_chainsaw/nonnegdef.py
verbose_chainsaw-0.1.1.dist-info/LICENSE
verbose_chainsaw-0.1.1.dist-info/METADATA
verbose_chainsaw-0.1.1.dist-info/WHEEL
verbose_chainsaw-0.1.1.dist-info/top_level.txt
verbose_chainsaw-0.1.1.dist-info/RECORD
