Metadata-Version: 2.1
Name: verbose-chainsaw
Version: 0.1.1
Summary: Pseudo-random matrix-valued data generator
Home-page: https://github.com/egoughnour/verbose-chainsaw
Author: E Goughnour
Author-email: e.goughnour@gmail.com
License: MIT
Classifier: Programming Language :: Python :: 3.8
Classifier: Programming Language :: Python :: 3.9
Classifier: Programming Language :: Python :: 3.10
Classifier: Programming Language :: Python :: 3.11
License-File: LICENSE
Requires-Dist: numpy
